{
    "10": {
        "initSale": {
            "auctionPeriod": 1209600,
            "delay": 3600,
            "miniAuctionPeriod": 21600,
            "periodMaxDiscount": 800000000000000000,
            "periodStartingPremium": 1200000000000000000,
            "reserveAutomationContracts": [
                "RESERVE_AUTOMATION_DAI",
                "RESERVE_AUTOMATION_WBTC",
                "RESERVE_AUTOMATION_wstETH",
                "RESERVE_AUTOMATION_cbETH",
                "RESERVE_AUTOMATION_rETH",
                "RESERVE_AUTOMATION_OP",
                "RESERVE_AUTOMATION_weETH",
                "RESERVE_AUTOMATION_VELO",
                "RESERVE_AUTOMATION_wrsETH"
            ]
        },
        "setMRDSpeeds": [
            {
                "emissionToken": "xWELL_PROXY",
                "market": "MOONWELL_USDC",
                "newBorrowSpeed": -1,
                "newEndTime": 1754623800,
                "newSupplySpeed": 160449790930704930
            },
            {
                "emissionToken": "OP",
                "market": "MOONWELL_USDC",
                "newBorrowSpeed": -1,
                "newEndTime": 1754623800,
                "newSupplySpeed": 4576570435190747
            },
            {
                "emissionToken": "xWELL_PROXY",
                "market": "MOONWELL_USDT",
                "newBorrowSpeed": -1,
                "newEndTime": 1754623800,
                "newSupplySpeed": -101382105225334
            },
            {
                "emissionToken": "OP",
                "market": "MOONWELL_USDT",
                "newBorrowSpeed": -1,
                "newEndTime": 1754623800,
                "newSupplySpeed": -2891760361545
            },
            {
                "emissionToken": "xWELL_PROXY",
                "market": "MOONWELL_DAI",
                "newBorrowSpeed": -1,
                "newEndTime": 1754623800,
                "newSupplySpeed": 4766962527496342
            },
            {
                "emissionToken": "OP",
                "market": "MOONWELL_DAI",
                "newBorrowSpeed": -1,
                "newEndTime": 1754623800,
                "newSupplySpeed": 135969885921659
            },
            {
                "emissionToken": "xWELL_PROXY",
                "market": "MOONWELL_WBTC",
                "newBorrowSpeed": -1,
                "newEndTime": 1754623800,
                "newSupplySpeed": -1
            },
            {
                "emissionToken": "OP",
                "market": "MOONWELL_WBTC",
                "newBorrowSpeed": -1,
                "newEndTime": 1754623800,
                "newSupplySpeed": -1
            },
            {
                "emissionToken": "xWELL_PROXY",
                "market": "MOONWELL_WETH",
                "newBorrowSpeed": -1,
                "newEndTime": 1754623800,
                "newSupplySpeed": 400433204606712900
            },
            {
                "emissionToken": "OP",
                "market": "MOONWELL_WETH",
                "newBorrowSpeed": -1,
                "newEndTime": 1754623800,
                "newSupplySpeed": 11421708653165132
            },
            {
                "emissionToken": "xWELL_PROXY",
                "market": "MOONWELL_wstETH",
                "newBorrowSpeed": -1,
                "newEndTime": 1754623800,
                "newSupplySpeed": 36144329927667930
            },
            {
                "emissionToken": "OP",
                "market": "MOONWELL_wstETH",
                "newBorrowSpeed": -1,
                "newEndTime": 1754623800,
                "newSupplySpeed": 1030958474842672
            },
            {
                "emissionToken": "xWELL_PROXY",
                "market": "MOONWELL_cbETH",
                "newBorrowSpeed": -1,
                "newEndTime": 1754623800,
                "newSupplySpeed": -1
            },
            {
                "emissionToken": "OP",
                "market": "MOONWELL_cbETH",
                "newBorrowSpeed": -1,
                "newEndTime": 1754623800,
                "newSupplySpeed": -1
            },
            {
                "emissionToken": "xWELL_PROXY",
                "market": "MOONWELL_rETH",
                "newBorrowSpeed": -1,
                "newEndTime": 1754623800,
                "newSupplySpeed": 3707612889451717
            },
            {
                "emissionToken": "OP",
                "market": "MOONWELL_rETH",
                "newBorrowSpeed": -1,
                "newEndTime": 1754623800,
                "newSupplySpeed": 105753653130811
            },
            {
                "emissionToken": "xWELL_PROXY",
                "market": "MOONWELL_OP",
                "newBorrowSpeed": -1,
                "newEndTime": 1754623800,
                "newSupplySpeed": 16825856519402700
            },
            {
                "emissionToken": "OP",
                "market": "MOONWELL_OP",
                "newBorrowSpeed": -1,
                "newEndTime": 1754623800,
                "newSupplySpeed": 479930307461209
            },
            {
                "emissionToken": "xWELL_PROXY",
                "market": "MOONWELL_weETH",
                "newBorrowSpeed": -1,
                "newEndTime": 1754623800,
                "newSupplySpeed": 38408361360105360
            },
            {
                "emissionToken": "OP",
                "market": "MOONWELL_weETH",
                "newBorrowSpeed": -1,
                "newEndTime": 1754623800,
                "newSupplySpeed": 1095536304816353
            },
            {
                "emissionToken": "xWELL_PROXY",
                "market": "MOONWELL_VELO",
                "newBorrowSpeed": -1,
                "newEndTime": 1754623800,
                "newSupplySpeed": 21444628910577564
            },
            {
                "emissionToken": "OP",
                "market": "MOONWELL_VELO",
                "newBorrowSpeed": -1,
                "newEndTime": 1754623800,
                "newSupplySpeed": 611673309740690
            },
            {
                "emissionToken": "xWELL_PROXY",
                "market": "MOONWELL_wrsETH",
                "newBorrowSpeed": -1,
                "newEndTime": 1754623800,
                "newSupplySpeed": 1100901102924695
            },
            {
                "emissionToken": "OP",
                "market": "MOONWELL_wrsETH",
                "newBorrowSpeed": -1,
                "newEndTime": 1754623800,
                "newSupplySpeed": 31401421033263
            },
            {
                "emissionToken": "xWELL_PROXY",
                "market": "MOONWELL_USDT0",
                "newBorrowSpeed": -1,
                "newEndTime": 1754623800,
                "newSupplySpeed": 41417907450975640
            },
            {
                "emissionToken": "OP",
                "market": "MOONWELL_USDT0",
                "newBorrowSpeed": -1,
                "newEndTime": 1754623800,
                "newSupplySpeed": 1181378733048430
            }
        ],
        "stkWellEmissionsPerSecond": 202136454821254800,
        "transferFrom": [
            {
                "amount": 4.999999e22,
                "from": "FOUNDATION_OP_MULTISIG",
                "to": "MRD_PROXY",
                "token": "OP"
            },
            {
                "amount": 1.7529478928330258e24,
                "from": "TEMPORAL_GOVERNOR",
                "to": "MRD_PROXY",
                "token": "xWELL_PROXY"
            }
        ],
        "transferReserves": [
            {
                "amount": 102739996455366800000,
                "market": "MOONWELL_DAI",
                "to": "RESERVE_AUTOMATION_DAI"
            },
            {
                "amount": 750,
                "market": "MOONWELL_WBTC",
                "to": "RESERVE_AUTOMATION_WBTC"
            },
            {
                "amount": 1324605044454576000,
                "market": "MOONWELL_wstETH",
                "to": "RESERVE_AUTOMATION_wstETH"
            },
            {
                "amount": 381973945974,
                "market": "MOONWELL_cbETH",
                "to": "RESERVE_AUTOMATION_cbETH"
            },
            {
                "amount": 965457349815670,
                "market": "MOONWELL_rETH",
                "to": "RESERVE_AUTOMATION_rETH"
            },
            {
                "amount": 248729099672791300000,
                "market": "MOONWELL_OP",
                "to": "RESERVE_AUTOMATION_OP"
            },
            {
                "amount": 4097298908269440,
                "market": "MOONWELL_weETH",
                "to": "RESERVE_AUTOMATION_weETH"
            },
            {
                "amount": 2.978848651105582e21,
                "market": "MOONWELL_VELO",
                "to": "RESERVE_AUTOMATION_VELO"
            },
            {
                "amount": 1524252023203030,
                "market": "MOONWELL_wrsETH",
                "to": "RESERVE_AUTOMATION_wrsETH"
            }
        ],
        "withdrawWell": [
            {
                "amount": 3.858939279839898e23,
                "to": "ECOSYSTEM_RESERVE_PROXY"
            }
        ],
        "multiRewarder": [
            {
                "addRewards": [
                    {
                        "distributor": "USDC_MULTI_REWARDER",
                        "duration": 2419200,
                        "rewardToken": "WELL"
                    },
                    {
                        "distributor": "USDC_MULTI_REWARDER",
                        "duration": 2419200,
                        "rewardToken": "OP"
                    }
                ],
                "notifyRewardAmount": [
                    {
                        "reward": 1.0311458151958975e23,
                        "rewardToken": "WELL"
                    },
                    {
                        "reward": 1e22,
                        "rewardToken": "OP"
                    }
                ],
                "vault": "USDC_MULTI_REWARDER"
            }
        ]
    },
    "1284": {
        "bridgeToRecipient": [
            {
                "amount": 1.0899574346522927e25,
                "nativeValue": 13987614151940264000,
                "network": 8453,
                "target": "TEMPORAL_GOVERNOR"
            },
            {
                "amount": 1.9591770778722055e24,
                "nativeValue": 13987614151940264000,
                "network": 10,
                "target": "TEMPORAL_GOVERNOR"
            },
            {
                "amount": 1.0311459251958976e23,
                "nativeValue": 13987614151940264000,
                "network": 10,
                "target": "DEX_RELAYER"
            }
        ],
        "transferFrom": [
            {
                "amount": 1.0899574436522927e25,
                "from": "MGLIMMER_MULTISIG",
                "to": "MULTICHAIN_GOVERNOR_PROXY",
                "token": "GOVTOKEN"
            },
            {
                "amount": 2.0622917503917952e24,
                "from": "MGLIMMER_MULTISIG",
                "to": "MULTICHAIN_GOVERNOR_PROXY",
                "token": "GOVTOKEN"
            },
            {
                "amount": 8.879081276811332e21,
                "from": "MGLIMMER_MULTISIG",
                "to": "MULTICHAIN_GOVERNOR_PROXY",
                "token": "GOVTOKEN"
            },
            {
                "amount": 8.523908425738877e22,
                "from": "MGLIMMER_MULTISIG",
                "to": "UNITROLLER",
                "token": "GOVTOKEN"
            },
            {
                "amount": 8.34632700020265e22,
                "from": "MGLIMMER_MULTISIG",
                "to": "ECOSYSTEM_RESERVE_PROXY",
                "token": "GOVTOKEN"
            }
        ],
        "addRewardInfo": {
            "amount": 8.879081276811332e21,
            "endTimestamp": 1754623800,
            "pid": 15,
            "rewardPerSec": 3670251023814207,
            "target": "STELLASWAP_REWARDER"
        },
        "setRewardSpeed": [
            {
                "market": "mGLIMMER",
                "newBorrowSpeed": 1449230859166862,
                "newSupplySpeed": 1449230859166862,
                "rewardType": 0
            },
            {
                "market": "mGLIMMER",
                "newBorrowSpeed": 3187866088205097,
                "newSupplySpeed": 3187866088205097,
                "rewardType": 1
            },
            {
                "market": "mxcDOT",
                "newBorrowSpeed": 1,
                "newSupplySpeed": 29837374850854970,
                "rewardType": 0
            },
            {
                "market": "mxcDOT",
                "newBorrowSpeed": 1,
                "newSupplySpeed": 65633128667150800,
                "rewardType": 1
            },
            {
                "market": "mFRAX",
                "newBorrowSpeed": 122496715530944,
                "newSupplySpeed": 122496715530944,
                "rewardType": 0
            },
            {
                "market": "mFRAX",
                "newBorrowSpeed": 269455430711775,
                "newSupplySpeed": 269455430711775,
                "rewardType": 1
            },
            {
                "market": "mETHwh",
                "newBorrowSpeed": 1,
                "newSupplySpeed": 0,
                "rewardType": 0
            },
            {
                "market": "mETHwh",
                "newBorrowSpeed": 1,
                "newSupplySpeed": 0,
                "rewardType": 1
            },
            {
                "market": "MOONWELL_mWBTC",
                "newBorrowSpeed": 1,
                "newSupplySpeed": 0,
                "rewardType": 0
            },
            {
                "market": "MOONWELL_mWBTC",
                "newBorrowSpeed": 1,
                "newSupplySpeed": 0,
                "rewardType": 1
            },
            {
                "market": "mUSDCwh",
                "newBorrowSpeed": 143966254500141,
                "newSupplySpeed": 143966254500141,
                "rewardType": 0
            },
            {
                "market": "mUSDCwh",
                "newBorrowSpeed": 316681871396764,
                "newSupplySpeed": 316681871396764,
                "rewardType": 1
            },
            {
                "market": "mxcUSDT",
                "newBorrowSpeed": 459459392240972,
                "newSupplySpeed": 459459392240972,
                "rewardType": 0
            },
            {
                "market": "mxcUSDT",
                "newBorrowSpeed": 1010670595487007,
                "newSupplySpeed": 1010670595487007,
                "rewardType": 1
            },
            {
                "market": "mxcUSDC",
                "newBorrowSpeed": 523364267441794,
                "newSupplySpeed": 523364267441794,
                "rewardType": 0
            },
            {
                "market": "mxcUSDC",
                "newBorrowSpeed": 1151241839354112,
                "newSupplySpeed": 1151241839354112,
                "rewardType": 1
            }
        ],
        "stkWellEmissionsPerSecond": 34500359623853544,
        "withdrawWell": []
    },
    "8453": {
        "initSale": {
            "auctionPeriod": 1209600,
            "delay": 3600,
            "miniAuctionPeriod": 21600,
            "periodMaxDiscount": 800000000000000000,
            "periodStartingPremium": 1200000000000000000,
            "reserveAutomationContracts": [
                "RESERVE_AUTOMATION_cbETH",
                "RESERVE_AUTOMATION_DAI",
                "RESERVE_AUTOMATION_USDC",
                "RESERVE_AUTOMATION_wstETH",
                "RESERVE_AUTOMATION_AERO",
                "RESERVE_AUTOMATION_weETH",
                "RESERVE_AUTOMATION_EURC",
                "RESERVE_AUTOMATION_LBTC",
                "RESERVE_AUTOMATION_VIRTUAL"
            ]
        },
        "setMRDSpeeds": [
            {
                "emissionToken": "xWELL_PROXY",
                "market": "MOONWELL_USDBC",
                "newBorrowSpeed": -1,
                "newEndTime": 1754623800,
                "newSupplySpeed": -1
            },
            {
                "emissionToken": "USDC",
                "market": "MOONWELL_USDBC",
                "newBorrowSpeed": -1,
                "newEndTime": -1,
                "newSupplySpeed": -1
            },
            {
                "emissionToken": "xWELL_PROXY",
                "market": "MOONWELL_WETH",
                "newBorrowSpeed": 399738566591554200,
                "newEndTime": 1754623800,
                "newSupplySpeed": 399738566591554200
            },
            {
                "emissionToken": "USDC",
                "market": "MOONWELL_WETH",
                "newBorrowSpeed": -1,
                "newEndTime": -1,
                "newSupplySpeed": -1
            },
            {
                "emissionToken": "xWELL_PROXY",
                "market": "MOONWELL_cbETH",
                "newBorrowSpeed": -1,
                "newEndTime": 1754623800,
                "newSupplySpeed": -1
            },
            {
                "emissionToken": "USDC",
                "market": "MOONWELL_cbETH",
                "newBorrowSpeed": -1,
                "newEndTime": -1,
                "newSupplySpeed": -1
            },
            {
                "emissionToken": "xWELL_PROXY",
                "market": "MOONWELL_DAI",
                "newBorrowSpeed": -1,
                "newEndTime": 1754623800,
                "newSupplySpeed": -1
            },
            {
                "emissionToken": "USDC",
                "market": "MOONWELL_DAI",
                "newBorrowSpeed": -1,
                "newEndTime": -1,
                "newSupplySpeed": -1
            },
            {
                "emissionToken": "xWELL_PROXY",
                "market": "MOONWELL_USDC",
                "newBorrowSpeed": -1,
                "newEndTime": 1754623800,
                "newSupplySpeed": 1441498943902783000
            },
            {
                "emissionToken": "USDC",
                "market": "MOONWELL_USDC",
                "newBorrowSpeed": -1,
                "newEndTime": -1,
                "newSupplySpeed": -1
            },
            {
                "emissionToken": "xWELL_PROXY",
                "market": "MOONWELL_wstETH",
                "newBorrowSpeed": -1,
                "newEndTime": 1754623800,
                "newSupplySpeed": -1
            },
            {
                "emissionToken": "USDC",
                "market": "MOONWELL_wstETH",
                "newBorrowSpeed": -1,
                "newEndTime": -1,
                "newSupplySpeed": -1
            },
            {
                "emissionToken": "xWELL_PROXY",
                "market": "MOONWELL_rETH",
                "newBorrowSpeed": -1,
                "newEndTime": 1754623800,
                "newSupplySpeed": -1
            },
            {
                "emissionToken": "USDC",
                "market": "MOONWELL_rETH",
                "newBorrowSpeed": -1,
                "newEndTime": -1,
                "newSupplySpeed": -1
            },
            {
                "emissionToken": "xWELL_PROXY",
                "market": "MOONWELL_AERO",
                "newBorrowSpeed": 64483855001435660,
                "newEndTime": 1754623800,
                "newSupplySpeed": 52759517728447360
            },
            {
                "emissionToken": "USDC",
                "market": "MOONWELL_AERO",
                "newBorrowSpeed": -1,
                "newEndTime": -1,
                "newSupplySpeed": -1
            },
            {
                "emissionToken": "xWELL_PROXY",
                "market": "MOONWELL_weETH",
                "newBorrowSpeed": -1,
                "newEndTime": 1754623800,
                "newSupplySpeed": -1
            },
            {
                "emissionToken": "USDC",
                "market": "MOONWELL_weETH",
                "newBorrowSpeed": -1,
                "newEndTime": -1,
                "newSupplySpeed": -1
            },
            {
                "emissionToken": "xWELL_PROXY",
                "market": "MOONWELL_cbBTC",
                "newBorrowSpeed": 211786280385083600,
                "newEndTime": 1754623800,
                "newSupplySpeed": 211786280385083600
            },
            {
                "emissionToken": "USDC",
                "market": "MOONWELL_cbBTC",
                "newBorrowSpeed": -1,
                "newEndTime": -1,
                "newSupplySpeed": -1
            },
            {
                "emissionToken": "xWELL_PROXY",
                "market": "MOONWELL_EURC",
                "newBorrowSpeed": 30372201235374970,
                "newEndTime": 1754623800,
                "newSupplySpeed": 30372201235374970
            },
            {
                "emissionToken": "USDC",
                "market": "MOONWELL_EURC",
                "newBorrowSpeed": -1,
                "newEndTime": -1,
                "newSupplySpeed": -1
            },
            {
                "emissionToken": "xWELL_PROXY",
                "market": "MOONWELL_wrsETH",
                "newBorrowSpeed": -1,
                "newEndTime": 1754623800,
                "newSupplySpeed": -1
            },
            {
                "emissionToken": "USDC",
                "market": "MOONWELL_wrsETH",
                "newBorrowSpeed": -1,
                "newEndTime": -1,
                "newSupplySpeed": -1
            },
            {
                "emissionToken": "xWELL_PROXY",
                "market": "MOONWELL_WELL",
                "newBorrowSpeed": 33302580402741940,
                "newEndTime": 1754623800,
                "newSupplySpeed": 27247565784061590
            },
            {
                "emissionToken": "USDC",
                "market": "MOONWELL_WELL",
                "newBorrowSpeed": -1,
                "newEndTime": -1,
                "newSupplySpeed": -1
            },
            {
                "emissionToken": "xWELL_PROXY",
                "market": "MOONWELL_USDS",
                "newBorrowSpeed": -1,
                "newEndTime": 1754623800,
                "newSupplySpeed": -1
            },
            {
                "emissionToken": "USDC",
                "market": "MOONWELL_USDS",
                "newBorrowSpeed": -1,
                "newEndTime": -1,
                "newSupplySpeed": -1
            },
            {
                "emissionToken": "xWELL_PROXY",
                "market": "MOONWELL_TBTC",
                "newBorrowSpeed": 5766109138470659,
                "newEndTime": 1754623800,
                "newSupplySpeed": 5766109138470659
            },
            {
                "emissionToken": "USDC",
                "market": "MOONWELL_TBTC",
                "newBorrowSpeed": -1,
                "newEndTime": -1,
                "newSupplySpeed": -1
            },
            {
                "emissionToken": "xWELL_PROXY",
                "market": "MOONWELL_LBTC",
                "newBorrowSpeed": 22776337311656696,
                "newEndTime": 1754623800,
                "newSupplySpeed": 22776337311656696
            },
            {
                "emissionToken": "USDC",
                "market": "MOONWELL_LBTC",
                "newBorrowSpeed": -1,
                "newEndTime": -1,
                "newSupplySpeed": -1
            },
            {
                "emissionToken": "xWELL_PROXY",
                "market": "MOONWELL_VIRTUAL",
                "newBorrowSpeed": 36921454618976376,
                "newEndTime": 1754623800,
                "newSupplySpeed": 30208462870071576
            },
            {
                "emissionToken": "USDC",
                "market": "MOONWELL_VIRTUAL",
                "newBorrowSpeed": -1,
                "newEndTime": -1,
                "newSupplySpeed": -1
            },
            {
                "emissionToken": "xWELL_PROXY",
                "market": "MOONWELL_MORPHO",
                "newBorrowSpeed": 42775955463200890,
                "newEndTime": 1754623800,
                "newSupplySpeed": 34998509015346180
            },
            {
                "emissionToken": "USDC",
                "market": "MOONWELL_MORPHO",
                "newBorrowSpeed": -1,
                "newEndTime": -1,
                "newSupplySpeed": -1
            },
            {
                "emissionToken": "xWELL_PROXY",
                "market": "MOONWELL_cbXRP",
                "newBorrowSpeed": 26804901507165670,
                "newEndTime": 1754623800,
                "newSupplySpeed": 21931283051317364
            },
            {
                "emissionToken": "USDC",
                "market": "MOONWELL_cbXRP",
                "newBorrowSpeed": -1,
                "newEndTime": -1,
                "newSupplySpeed": -1
            }
        ],
        "stkWellEmissionsPerSecond": 5182330449041585000,
        "transferFrom": [
            {
                "amount": 7.629702025566049e24,
                "from": "TEMPORAL_GOVERNOR",
                "to": "MRD_PROXY",
                "token": "xWELL_PROXY"
            },
            {
                "amount": 6.0019192879185e23,
                "from": "F-AERO_MULTISIG",
                "to": "DEX_RELAYER",
                "token": "xWELL_PROXY"
            }
        ],
        "transferReserves": [
            {
                "amount": 35626208625463000,
                "market": "MOONWELL_cbETH",
                "to": "RESERVE_AUTOMATION_cbETH"
            },
            {
                "amount": 90269764843199700000,
                "market": "MOONWELL_DAI",
                "to": "RESERVE_AUTOMATION_DAI"
            },
            {
                "amount": 263428419423,
                "market": "MOONWELL_USDC",
                "to": "RESERVE_AUTOMATION_USDC"
            },
            {
                "amount": 19454266552674000,
                "market": "MOONWELL_wstETH",
                "to": "RESERVE_AUTOMATION_wstETH"
            },
            {
                "amount": 2.852288817484946e22,
                "market": "MOONWELL_AERO",
                "to": "RESERVE_AUTOMATION_AERO"
            },
            {
                "amount": 387735011230394000,
                "market": "MOONWELL_weETH",
                "to": "RESERVE_AUTOMATION_weETH"
            },
            {
                "amount": 11277928416,
                "market": "MOONWELL_EURC",
                "to": "RESERVE_AUTOMATION_EURC"
            },
            {
                "amount": 197524,
                "market": "MOONWELL_LBTC",
                "to": "RESERVE_AUTOMATION_LBTC"
            },
            {
                "amount": 2.497544886271737e21,
                "market": "MOONWELL_VIRTUAL",
                "to": "RESERVE_AUTOMATION_VIRTUAL"
            }
        ],
        "withdrawWell": [
            {
                "amount": 9.267221520364524e24,
                "to": "ECOSYSTEM_RESERVE_PROXY"
            }
        ]
    },
    "endTimeSTamp": 1754623800,
    "startTimeStamp": 1752204600
}
